nlannuzel/sgrain/__init__.py
nlannuzel/sgrain/__main__.py
nlannuzel/sgrain/geo.py
nlannuzel/sgrain/graph.py
nlannuzel/sgrain/rain.py
nlannuzel_sgrain-1.0.9.dist-info/licenses/LICENSE
nlannuzel_sgrain-1.0.9.dist-info/METADATA
nlannuzel_sgrain-1.0.9.dist-info/WHEEL
nlannuzel_sgrain-1.0.9.dist-info/entry_points.txt
nlannuzel_sgrain-1.0.9.dist-info/top_level.txt
nlannuzel_sgrain-1.0.9.dist-info/RECORD
