Metadata-Version: 2.4
Name: nlannuzel.sgrain
Version: 1.0.9
Summary: Tells if, and how hard, it's raining at any location in Singapore
Author-email: Nicolas Lannuzel <nlannuzel@gmail.com>
Project-URL: Homepage, https://github.com/nlannuzel/sgrain
Keywords: weather,rain,radar,singapore
Classifier: Programming Language :: Python :: 3
Classifier: Operating System :: OS Independent
Classifier: Development Status :: 4 - Beta
Classifier: License :: OSI Approved :: GNU General Public License v3 (GPLv3)
Classifier: Topic :: Home Automation
Requires-Python: >=3.11
License-File: LICENSE
Requires-Dist: pypng
Dynamic: license-file
